{
  "generated_at": "2026-01-17T07:54:53.540535+00:00",
  "total_domains": 92,
  "domains": [
    {
      "domain": "24resor.se",
      "tld": "se",
      "release_date": "2026-01-18",
      "available": true,
      "indexed": true,
      "estimated_pages": null,
      "index_source": "google",
      "checked_at": "2026-01-17T07:54:53.540535+00:00"
    },
    {
      "domain": "2natur.se",
      "tld": "se",
      "release_date": "2026-01-18",
      "available": true,
      "indexed": true,
      "estimated_pages": null,
      "index_source": "google",
      "checked_at": "2026-01-17T07:54:53.540535+00:00"
    },
    {
      "domain": "3dtanja.se",
      "tld": "se",
      "release_date": "2026-01-18",
      "available": true,
      "indexed": true,
      "estimated_pages": null,
      "index_source": "google",
      "checked_at": "2026-01-17T07:54:53.540535+00:00"
    },
    {
      "domain": "4rtisprotein.se",
      "tld": "se",
      "release_date": "2026-01-18",
      "available": true,
      "indexed": true,
      "estimated_pages": null,
      "index_source": "google",
      "checked_at": "2026-01-17T07:54:53.540535+00:00"
    },
    {
      "domain": "academicsupport.se",
      "tld": "se",
      "release_date": "2026-01-18",
      "available": true,
      "indexed": true,
      "estimated_pages": null,
      "index_source": "google",
      "checked_at": "2026-01-17T07:54:53.540535+00:00"
    },
    {
      "domain": "acceleramb.se",
      "tld": "se",
      "release_date": "2026-01-18",
      "available": true,
      "indexed": true,
      "estimated_pages": null,
      "index_source": "google",
      "checked_at": "2026-01-17T07:54:53.540535+00:00"
    },
    {
      "domain": "accelerated.se",
      "tld": "se",
      "release_date": "2026-01-18",
      "available": true,
      "indexed": true,
      "estimated_pages": null,
      "index_source": "google",
      "checked_at": "2026-01-17T07:54:53.540535+00:00"
    },
    {
      "domain": "acecomdevelopment.se",
      "tld": "se",
      "release_date": "2026-01-18",
      "available": true,
      "indexed": true,
      "estimated_pages": null,
      "index_source": "google",
      "checked_at": "2026-01-17T07:54:53.540535+00:00"
    },
    {
      "domain": "acl-wp.se",
      "tld": "se",
      "release_date": "2026-01-18",
      "available": true,
      "indexed": true,
      "estimated_pages": null,
      "index_source": "google",
      "checked_at": "2026-01-17T07:54:53.540535+00:00"
    },
    {
      "domain": "adsol.se",
      "tld": "se",
      "release_date": "2026-01-18",
      "available": true,
      "indexed": true,
      "estimated_pages": null,
      "index_source": "google",
      "checked_at": "2026-01-17T07:54:53.540535+00:00"
    },
    {
      "domain": "afrapharma.se",
      "tld": "se",
      "release_date": "2026-01-18",
      "available": true,
      "indexed": true,
      "estimated_pages": null,
      "index_source": "google",
      "checked_at": "2026-01-17T07:54:53.540535+00:00"
    },
    {
      "domain": "akkadian.se",
      "tld": "se",
      "release_date": "2026-01-18",
      "available": true,
      "indexed": true,
      "estimated_pages": null,
      "index_source": "google",
      "checked_at": "2026-01-17T07:54:53.540535+00:00"
    },
    {
      "domain": "aknemedicin.se",
      "tld": "se",
      "release_date": "2026-01-18",
      "available": true,
      "indexed": true,
      "estimated_pages": null,
      "index_source": "google",
      "checked_at": "2026-01-17T07:54:53.540535+00:00"
    },
    {
      "domain": "alefiskarna.se",
      "tld": "se",
      "release_date": "2026-01-18",
      "available": true,
      "indexed": true,
      "estimated_pages": null,
      "index_source": "google",
      "checked_at": "2026-01-17T07:54:53.540535+00:00"
    },
    {
      "domain": "alexandersfix.se",
      "tld": "se",
      "release_date": "2026-01-18",
      "available": true,
      "indexed": true,
      "estimated_pages": null,
      "index_source": "google",
      "checked_at": "2026-01-17T07:54:53.540535+00:00"
    },
    {
      "domain": "allabolags.se",
      "tld": "se",
      "release_date": "2026-01-18",
      "available": true,
      "indexed": true,
      "estimated_pages": null,
      "index_source": "google",
      "checked_at": "2026-01-17T07:54:53.540535+00:00"
    },
    {
      "domain": "allconplate.se",
      "tld": "se",
      "release_date": "2026-01-18",
      "available": true,
      "indexed": true,
      "estimated_pages": null,
      "index_source": "google",
      "checked_at": "2026-01-17T07:54:53.540535+00:00"
    },
    {
      "domain": "allhalsa.se",
      "tld": "se",
      "release_date": "2026-01-18",
      "available": true,
      "indexed": true,
      "estimated_pages": null,
      "index_source": "google",
      "checked_at": "2026-01-17T07:54:53.540535+00:00"
    },
    {
      "domain": "allinmindpublishing.se",
      "tld": "se",
      "release_date": "2026-01-18",
      "available": true,
      "indexed": true,
      "estimated_pages": null,
      "index_source": "google",
      "checked_at": "2026-01-17T07:54:53.540535+00:00"
    },
    {
      "domain": "alltjanstkalix.se",
      "tld": "se",
      "release_date": "2026-01-18",
      "available": true,
      "indexed": true,
      "estimated_pages": null,
      "index_source": "google",
      "checked_at": "2026-01-17T07:54:53.540535+00:00"
    },
    {
      "domain": "almablom.se",
      "tld": "se",
      "release_date": "2026-01-18",
      "available": true,
      "indexed": true,
      "estimated_pages": null,
      "index_source": "google",
      "checked_at": "2026-01-17T07:54:53.540535+00:00"
    },
    {
      "domain": "alridwan.se",
      "tld": "se",
      "release_date": "2026-01-18",
      "available": true,
      "indexed": true,
      "estimated_pages": null,
      "index_source": "google",
      "checked_at": "2026-01-17T07:54:53.540535+00:00"
    },
    {
      "domain": "alternatingcurrent.se",
      "tld": "se",
      "release_date": "2026-01-18",
      "available": true,
      "indexed": true,
      "estimated_pages": null,
      "index_source": "google",
      "checked_at": "2026-01-17T07:54:53.540535+00:00"
    },
    {
      "domain": "altiorehalsa.se",
      "tld": "se",
      "release_date": "2026-01-18",
      "available": true,
      "indexed": true,
      "estimated_pages": null,
      "index_source": "google",
      "checked_at": "2026-01-17T07:54:53.540535+00:00"
    },
    {
      "domain": "alutile.se",
      "tld": "se",
      "release_date": "2026-01-18",
      "available": true,
      "indexed": true,
      "estimated_pages": null,
      "index_source": "google",
      "checked_at": "2026-01-17T07:54:53.540535+00:00"
    },
    {
      "domain": "amandawester.se",
      "tld": "se",
      "release_date": "2026-01-18",
      "available": true,
      "indexed": true,
      "estimated_pages": null,
      "index_source": "google",
      "checked_at": "2026-01-17T07:54:53.540535+00:00"
    },
    {
      "domain": "amelieochhans.se",
      "tld": "se",
      "release_date": "2026-01-18",
      "available": true,
      "indexed": true,
      "estimated_pages": null,
      "index_source": "google",
      "checked_at": "2026-01-17T07:54:53.540535+00:00"
    },
    {
      "domain": "amotjaktskytte.se",
      "tld": "se",
      "release_date": "2026-01-18",
      "available": true,
      "indexed": true,
      "estimated_pages": null,
      "index_source": "google",
      "checked_at": "2026-01-17T07:54:53.540535+00:00"
    },
    {
      "domain": "angbyninvest.se",
      "tld": "se",
      "release_date": "2026-01-18",
      "available": true,
      "indexed": true,
      "estimated_pages": null,
      "index_source": "google",
      "checked_at": "2026-01-17T07:54:53.540535+00:00"
    },
    {
      "domain": "arch-vile.se",
      "tld": "se",
      "release_date": "2026-01-18",
      "available": true,
      "indexed": true,
      "estimated_pages": null,
      "index_source": "google",
      "checked_at": "2026-01-17T07:54:53.540535+00:00"
    },
    {
      "domain": "arcticsoul.se",
      "tld": "se",
      "release_date": "2026-01-18",
      "available": true,
      "indexed": true,
      "estimated_pages": null,
      "index_source": "google",
      "checked_at": "2026-01-17T07:54:53.540535+00:00"
    },
    {
      "domain": "arecamping.se",
      "tld": "se",
      "release_date": "2026-01-18",
      "available": true,
      "indexed": true,
      "estimated_pages": null,
      "index_source": "google",
      "checked_at": "2026-01-17T07:54:53.540535+00:00"
    },
    {
      "domain": "arstabilvard.se",
      "tld": "se",
      "release_date": "2026-01-18",
      "available": true,
      "indexed": true,
      "estimated_pages": null,
      "index_source": "google",
      "checked_at": "2026-01-17T07:54:53.540535+00:00"
    },
    {
      "domain": "artbymoments.se",
      "tld": "se",
      "release_date": "2026-01-18",
      "available": true,
      "indexed": true,
      "estimated_pages": null,
      "index_source": "google",
      "checked_at": "2026-01-17T07:54:53.540535+00:00"
    },
    {
      "domain": "artproof.se",
      "tld": "se",
      "release_date": "2026-01-18",
      "available": true,
      "indexed": true,
      "estimated_pages": null,
      "index_source": "google",
      "checked_at": "2026-01-17T07:54:53.540535+00:00"
    },
    {
      "domain": "atelje-eljest.se",
      "tld": "se",
      "release_date": "2026-01-18",
      "available": true,
      "indexed": true,
      "estimated_pages": null,
      "index_source": "google",
      "checked_at": "2026-01-17T07:54:53.540535+00:00"
    },
    {
      "domain": "atletico.se",
      "tld": "se",
      "release_date": "2026-01-18",
      "available": true,
      "indexed": true,
      "estimated_pages": null,
      "index_source": "google",
      "checked_at": "2026-01-17T07:54:53.540535+00:00"
    },
    {
      "domain": "atm-performancekalmar.se",
      "tld": "se",
      "release_date": "2026-01-18",
      "available": true,
      "indexed": true,
      "estimated_pages": null,
      "index_source": "google",
      "checked_at": "2026-01-17T07:54:53.540535+00:00"
    },
    {
      "domain": "autodealer.se",
      "tld": "se",
      "release_date": "2026-01-18",
      "available": true,
      "indexed": true,
      "estimated_pages": null,
      "index_source": "google",
      "checked_at": "2026-01-17T07:54:53.540535+00:00"
    },
    {
      "domain": "autotiler.se",
      "tld": "se",
      "release_date": "2026-01-18",
      "available": true,
      "indexed": true,
      "estimated_pages": null,
      "index_source": "google",
      "checked_at": "2026-01-17T07:54:53.540535+00:00"
    },
    {
      "domain": "bakplat.se",
      "tld": "se",
      "release_date": "2026-01-18",
      "available": true,
      "indexed": true,
      "estimated_pages": null,
      "index_source": "google",
      "checked_at": "2026-01-17T07:54:53.540535+00:00"
    },
    {
      "domain": "bakterier.se",
      "tld": "se",
      "release_date": "2026-01-18",
      "available": true,
      "indexed": true,
      "estimated_pages": null,
      "index_source": "google",
      "checked_at": "2026-01-17T07:54:53.540535+00:00"
    },
    {
      "domain": "bambukudden.se",
      "tld": "se",
      "release_date": "2026-01-18",
      "available": true,
      "indexed": true,
      "estimated_pages": null,
      "index_source": "google",
      "checked_at": "2026-01-17T07:54:53.540535+00:00"
    },
    {
      "domain": "batmassamarstrand.se",
      "tld": "se",
      "release_date": "2026-01-18",
      "available": true,
      "indexed": true,
      "estimated_pages": null,
      "index_source": "google",
      "checked_at": "2026-01-17T07:54:53.540535+00:00"
    },
    {
      "domain": "bbsbildelar.se",
      "tld": "se",
      "release_date": "2026-01-18",
      "available": true,
      "indexed": true,
      "estimated_pages": null,
      "index_source": "google",
      "checked_at": "2026-01-17T07:54:53.540535+00:00"
    },
    {
      "domain": "bbsinvest.se",
      "tld": "se",
      "release_date": "2026-01-18",
      "available": true,
      "indexed": true,
      "estimated_pages": null,
      "index_source": "google",
      "checked_at": "2026-01-17T07:54:53.540535+00:00"
    },
    {
      "domain": "beana.se",
      "tld": "se",
      "release_date": "2026-01-18",
      "available": true,
      "indexed": true,
      "estimated_pages": null,
      "index_source": "google",
      "checked_at": "2026-01-17T07:54:53.540535+00:00"
    },
    {
      "domain": "belife.se",
      "tld": "se",
      "release_date": "2026-01-18",
      "available": true,
      "indexed": true,
      "estimated_pages": null,
      "index_source": "google",
      "checked_at": "2026-01-17T07:54:53.540535+00:00"
    },
    {
      "domain": "beredskapsfronten.se",
      "tld": "se",
      "release_date": "2026-01-18",
      "available": true,
      "indexed": true,
      "estimated_pages": null,
      "index_source": "google",
      "checked_at": "2026-01-17T07:54:53.540535+00:00"
    },
    {
      "domain": "beredskapsstyrkan.se",
      "tld": "se",
      "release_date": "2026-01-18",
      "available": true,
      "indexed": true,
      "estimated_pages": null,
      "index_source": "google",
      "checked_at": "2026-01-17T07:54:53.540535+00:00"
    },
    {
      "domain": "besiktasolel.se",
      "tld": "se",
      "release_date": "2026-01-18",
      "available": true,
      "indexed": true,
      "estimated_pages": null,
      "index_source": "google",
      "checked_at": "2026-01-17T07:54:53.540535+00:00"
    },
    {
      "domain": "besiktningstekniker.se",
      "tld": "se",
      "release_date": "2026-01-18",
      "available": true,
      "indexed": true,
      "estimated_pages": null,
      "index_source": "google",
      "checked_at": "2026-01-17T07:54:53.540535+00:00"
    },
    {
      "domain": "beslagtaget.se",
      "tld": "se",
      "release_date": "2026-01-18",
      "available": true,
      "indexed": true,
      "estimated_pages": null,
      "index_source": "google",
      "checked_at": "2026-01-17T07:54:53.540535+00:00"
    },
    {
      "domain": "best-marine.se",
      "tld": "se",
      "release_date": "2026-01-18",
      "available": true,
      "indexed": true,
      "estimated_pages": null,
      "index_source": "google",
      "checked_at": "2026-01-17T07:54:53.540535+00:00"
    },
    {
      "domain": "better-jute.se",
      "tld": "se",
      "release_date": "2026-01-18",
      "available": true,
      "indexed": true,
      "estimated_pages": null,
      "index_source": "google",
      "checked_at": "2026-01-17T07:54:53.540535+00:00"
    },
    {
      "domain": "bilhandlarpriser.se",
      "tld": "se",
      "release_date": "2026-01-18",
      "available": true,
      "indexed": true,
      "estimated_pages": null,
      "index_source": "google",
      "checked_at": "2026-01-17T07:54:53.540535+00:00"
    },
    {
      "domain": "billigaballonger.se",
      "tld": "se",
      "release_date": "2026-01-18",
      "available": true,
      "indexed": true,
      "estimated_pages": null,
      "index_source": "google",
      "checked_at": "2026-01-17T07:54:53.540535+00:00"
    },
    {
      "domain": "bitcoinkollen.se",
      "tld": "se",
      "release_date": "2026-01-18",
      "available": true,
      "indexed": true,
      "estimated_pages": null,
      "index_source": "google",
      "checked_at": "2026-01-17T07:54:53.540535+00:00"
    },
    {
      "domain": "bitcoinsnack.se",
      "tld": "se",
      "release_date": "2026-01-18",
      "available": true,
      "indexed": true,
      "estimated_pages": null,
      "index_source": "google",
      "checked_at": "2026-01-17T07:54:53.540535+00:00"
    },
    {
      "domain": "bjellverud.se",
      "tld": "se",
      "release_date": "2026-01-18",
      "available": true,
      "indexed": true,
      "estimated_pages": null,
      "index_source": "google",
      "checked_at": "2026-01-17T07:54:53.540535+00:00"
    },
    {
      "domain": "bjorklingecentrum.se",
      "tld": "se",
      "release_date": "2026-01-18",
      "available": true,
      "indexed": true,
      "estimated_pages": null,
      "index_source": "google",
      "checked_at": "2026-01-17T07:54:53.540535+00:00"
    },
    {
      "domain": "blaamax.se",
      "tld": "se",
      "release_date": "2026-01-18",
      "available": true,
      "indexed": true,
      "estimated_pages": null,
      "index_source": "google",
      "checked_at": "2026-01-17T07:54:53.540535+00:00"
    },
    {
      "domain": "blamax.se",
      "tld": "se",
      "release_date": "2026-01-18",
      "available": true,
      "indexed": true,
      "estimated_pages": null,
      "index_source": "google",
      "checked_at": "2026-01-17T07:54:53.540535+00:00"
    },
    {
      "domain": "blossband.se",
      "tld": "se",
      "release_date": "2026-01-18",
      "available": true,
      "indexed": true,
      "estimated_pages": null,
      "index_source": "google",
      "checked_at": "2026-01-17T07:54:53.540535+00:00"
    },
    {
      "domain": "boarpsdalen.se",
      "tld": "se",
      "release_date": "2026-01-18",
      "available": true,
      "indexed": true,
      "estimated_pages": null,
      "index_source": "google",
      "checked_at": "2026-01-17T07:54:53.540535+00:00"
    },
    {
      "domain": "bordsflakt.se",
      "tld": "se",
      "release_date": "2026-01-18",
      "available": true,
      "indexed": true,
      "estimated_pages": null,
      "index_source": "google",
      "checked_at": "2026-01-17T07:54:53.540535+00:00"
    },
    {
      "domain": "brahls.se",
      "tld": "se",
      "release_date": "2026-01-18",
      "available": true,
      "indexed": true,
      "estimated_pages": null,
      "index_source": "google",
      "checked_at": "2026-01-17T07:54:53.540535+00:00"
    },
    {
      "domain": "brearedskaningard.se",
      "tld": "se",
      "release_date": "2026-01-18",
      "available": true,
      "indexed": true,
      "estimated_pages": null,
      "index_source": "google",
      "checked_at": "2026-01-17T07:54:53.540535+00:00"
    },
    {
      "domain": "britera.se",
      "tld": "se",
      "release_date": "2026-01-18",
      "available": true,
      "indexed": true,
      "estimated_pages": null,
      "index_source": "google",
      "checked_at": "2026-01-17T07:54:53.540535+00:00"
    },
    {
      "domain": "bugrace.se",
      "tld": "se",
      "release_date": "2026-01-18",
      "available": true,
      "indexed": true,
      "estimated_pages": null,
      "index_source": "google",
      "checked_at": "2026-01-17T07:54:53.540535+00:00"
    },
    {
      "domain": "buildiver.se",
      "tld": "se",
      "release_date": "2026-01-18",
      "available": true,
      "indexed": true,
      "estimated_pages": null,
      "index_source": "google",
      "checked_at": "2026-01-17T07:54:53.540535+00:00"
    },
    {
      "domain": "byggfirmastrangnas.se",
      "tld": "se",
      "release_date": "2026-01-18",
      "available": true,
      "indexed": true,
      "estimated_pages": null,
      "index_source": "google",
      "checked_at": "2026-01-17T07:54:53.540535+00:00"
    },
    {
      "domain": "byggtryggsverige.se",
      "tld": "se",
      "release_date": "2026-01-18",
      "available": true,
      "indexed": true,
      "estimated_pages": null,
      "index_source": "google",
      "checked_at": "2026-01-17T07:54:53.540535+00:00"
    },
    {
      "domain": "bytavindrutamalmo.se",
      "tld": "se",
      "release_date": "2026-01-18",
      "available": true,
      "indexed": true,
      "estimated_pages": null,
      "index_source": "google",
      "checked_at": "2026-01-17T07:54:53.540535+00:00"
    },
    {
      "domain": "cadiz.se",
      "tld": "se",
      "release_date": "2026-01-18",
      "available": true,
      "indexed": true,
      "estimated_pages": null,
      "index_source": "google",
      "checked_at": "2026-01-17T07:54:53.540535+00:00"
    },
    {
      "domain": "canasta.se",
      "tld": "se",
      "release_date": "2026-01-18",
      "available": true,
      "indexed": true,
      "estimated_pages": null,
      "index_source": "google",
      "checked_at": "2026-01-17T07:54:53.540535+00:00"
    },
    {
      "domain": "carltinnsten.se",
      "tld": "se",
      "release_date": "2026-01-18",
      "available": true,
      "indexed": true,
      "estimated_pages": null,
      "index_source": "google",
      "checked_at": "2026-01-17T07:54:53.540535+00:00"
    },
    {
      "domain": "cataniaclub.se",
      "tld": "se",
      "release_date": "2026-01-18",
      "available": true,
      "indexed": true,
      "estimated_pages": null,
      "index_source": "google",
      "checked_at": "2026-01-17T07:54:53.540535+00:00"
    },
    {
      "domain": "cbsnickeri.se",
      "tld": "se",
      "release_date": "2026-01-18",
      "available": true,
      "indexed": true,
      "estimated_pages": null,
      "index_source": "google",
      "checked_at": "2026-01-17T07:54:53.540535+00:00"
    },
    {
      "domain": "changebloggen.se",
      "tld": "se",
      "release_date": "2026-01-18",
      "available": true,
      "indexed": true,
      "estimated_pages": null,
      "index_source": "google",
      "checked_at": "2026-01-17T07:54:53.540535+00:00"
    },
    {
      "domain": "changeproductions.se",
      "tld": "se",
      "release_date": "2026-01-18",
      "available": true,
      "indexed": true,
      "estimated_pages": null,
      "index_source": "google",
      "checked_at": "2026-01-17T07:54:53.540535+00:00"
    },
    {
      "domain": "changesociety.se",
      "tld": "se",
      "release_date": "2026-01-18",
      "available": true,
      "indexed": true,
      "estimated_pages": null,
      "index_source": "google",
      "checked_at": "2026-01-17T07:54:53.540535+00:00"
    },
    {
      "domain": "chatbuddy.se",
      "tld": "se",
      "release_date": "2026-01-18",
      "available": true,
      "indexed": true,
      "estimated_pages": null,
      "index_source": "google",
      "checked_at": "2026-01-17T07:54:53.540535+00:00"
    },
    {
      "domain": "cheekysuprise.se",
      "tld": "se",
      "release_date": "2026-01-18",
      "available": true,
      "indexed": true,
      "estimated_pages": null,
      "index_source": "google",
      "checked_at": "2026-01-17T07:54:53.540535+00:00"
    },
    {
      "domain": "chi-performance.se",
      "tld": "se",
      "release_date": "2026-01-18",
      "available": true,
      "indexed": true,
      "estimated_pages": null,
      "index_source": "google",
      "checked_at": "2026-01-17T07:54:53.540535+00:00"
    },
    {
      "domain": "chinesewhispers.se",
      "tld": "se",
      "release_date": "2026-01-18",
      "available": true,
      "indexed": true,
      "estimated_pages": null,
      "index_source": "google",
      "checked_at": "2026-01-17T07:54:53.540535+00:00"
    },
    {
      "domain": "chocho.se",
      "tld": "se",
      "release_date": "2026-01-18",
      "available": true,
      "indexed": true,
      "estimated_pages": null,
      "index_source": "google",
      "checked_at": "2026-01-17T07:54:53.540535+00:00"
    },
    {
      "domain": "cito-share.se",
      "tld": "se",
      "release_date": "2026-01-18",
      "available": true,
      "indexed": true,
      "estimated_pages": null,
      "index_source": "google",
      "checked_at": "2026-01-17T07:54:53.540535+00:00"
    },
    {
      "domain": "ckshapeclinic.se",
      "tld": "se",
      "release_date": "2026-01-18",
      "available": true,
      "indexed": true,
      "estimated_pages": null,
      "index_source": "google",
      "checked_at": "2026-01-17T07:54:53.540535+00:00"
    },
    {
      "domain": "clickandplay.se",
      "tld": "se",
      "release_date": "2026-01-18",
      "available": true,
      "indexed": true,
      "estimated_pages": null,
      "index_source": "google",
      "checked_at": "2026-01-17T07:54:53.540535+00:00"
    },
    {
      "domain": "lovehomeshop.nu",
      "tld": "nu",
      "release_date": "2026-01-18",
      "available": true,
      "indexed": true,
      "estimated_pages": null,
      "index_source": "google",
      "checked_at": "2026-01-17T07:54:53.540535+00:00"
    },
    {
      "domain": "phomemostore.se",
      "tld": "se",
      "release_date": "2026-01-18",
      "available": true,
      "indexed": true,
      "estimated_pages": null,
      "index_source": "google",
      "checked_at": "2026-01-17T07:54:53.540535+00:00"
    }
  ]
}